orthopoly/__init__.py
orthopoly/chebyshev.py
orthopoly/gegenbauer.py
orthopoly/legendre.py
orthopoly/spherical_harmonic.py
orthopoly/util.py
orthopoly-0.9.4.dist-info/LICENSE
orthopoly-0.9.4.dist-info/METADATA
orthopoly-0.9.4.dist-info/WHEEL
orthopoly-0.9.4.dist-info/top_level.txt
orthopoly-0.9.4.dist-info/RECORD
