Metadata-Version: 2.1
Name: orthopoly
Version: 0.9.4
Summary: Python functions for orthogonal polynomials and (real, 2D, orthonormal) spherical harmonics
Home-page: https://github.com/markmbaum/orthopoly
Author: Mark Baum <markmbaum@protonmail.com>
Author-email: markmbaum@protonmail.com
License: UNKNOWN
Platform: UNKNOWN
Classifier: Programming Language :: Python :: 3
Classifier: License :: OSI Approved :: MIT License
Classifier: Operating System :: OS Independent
Requires-Python: >=3
Requires-Dist: numpy
Requires-Dist: scipy (>=1.5.4)
